haystack_integrations/components/connectors/py.typed
haystack_integrations/components/connectors/jina/__init__.py
haystack_integrations/components/connectors/jina/reader.py
haystack_integrations/components/connectors/jina/reader_mode.py
haystack_integrations/components/embedders/py.typed
haystack_integrations/components/embedders/jina/__init__.py
haystack_integrations/components/embedders/jina/document_embedder.py
haystack_integrations/components/embedders/jina/document_image_embedder.py
haystack_integrations/components/embedders/jina/text_embedder.py
haystack_integrations/components/rankers/jina/__init__.py
haystack_integrations/components/rankers/jina/ranker.py
jina_haystack-1.1.0.dist-info/METADATA
jina_haystack-1.1.0.dist-info/WHEEL
jina_haystack-1.1.0.dist-info/licenses/LICENSE.txt
jina_haystack-1.1.0.dist-info/RECORD
